rfactor/__init__.py
rfactor/process.py
rfactor/rain.py
rfactor/rfactor.py
rfactor/valid.py
rfactor/matlab/core.m
rfactor/matlab/main.m
rfactor-0.1.4.dist-info/licenses/AUTHORS.rst
rfactor-0.1.4.dist-info/licenses/LICENSE
rfactor-0.1.4.dist-info/METADATA
rfactor-0.1.4.dist-info/WHEEL
rfactor-0.1.4.dist-info/top_level.txt
rfactor-0.1.4.dist-info/RECORD
