Metadata-Version: 2.4
Name: rfactor
Version: 0.1.4
Summary: Scripts to compute and analyse the RUSLE R-factor.
Home-page: https://github.com/watem-sedem/rfactor
Author: Sacha Gobeyn
Author-email: sacha@fluves.com
License: LGPL-3
Project-URL: Documentation, https://watem-sedem.github.io/rfactor/
Project-URL: Source, https://github.com/watem-sedem/rfactor
Project-URL: Changelog, https://watem-sedem.github.io/rfactor/changelog.html
Platform: any
Classifier: Development Status :: 4 - Beta
Classifier: Programming Language :: Python
Classifier: Intended Audience :: Science/Research
License-File: LICENSE
License-File: AUTHORS.rst
Requires-Dist: importlib-metadata<4.3,>=1.1.0; python_version < "3.8"
Requires-Dist: pandas
Requires-Dist: numpy
Requires-Dist: matplotlib
Requires-Dist: tqdm
Requires-Dist: python-dotenv
Requires-Dist: joblib
Requires-Dist: tqdm
Provides-Extra: develop
Requires-Dist: pytest; extra == "develop"
Requires-Dist: pytest-cov; extra == "develop"
Requires-Dist: pytest-xdist; extra == "develop"
Requires-Dist: sphinx; extra == "develop"
Requires-Dist: sphinx_rtd_theme; extra == "develop"
Requires-Dist: nbsphinx; extra == "develop"
Requires-Dist: jupyter; extra == "develop"
Requires-Dist: pre-commit; extra == "develop"
Requires-Dist: black; extra == "develop"
Requires-Dist: flake8; extra == "develop"
Requires-Dist: pytest-datafiles; extra == "develop"
Requires-Dist: tox; extra == "develop"
Requires-Dist: sphinx-copybutton; extra == "develop"
Requires-Dist: interrogate; extra == "develop"
Requires-Dist: nbstripout; extra == "develop"
Requires-Dist: setuptools_scm; extra == "develop"
Requires-Dist: virtualenv; extra == "develop"
Dynamic: license-file
